setup.py
vdt/__init__.py
vdt.versionplugin.puppetforge.egg-info/PKG-INFO
vdt.versionplugin.puppetforge.egg-info/SOURCES.txt
vdt.versionplugin.puppetforge.egg-info/dependency_links.txt
vdt.versionplugin.puppetforge.egg-info/namespace_packages.txt
vdt.versionplugin.puppetforge.egg-info/requires.txt
vdt.versionplugin.puppetforge.egg-info/top_level.txt
vdt.versionplugin.puppetforge.egg-info/zip-safe
vdt/versionplugin/__init__.py
vdt/versionplugin/puppetforge/__init__.py
vdt/versionplugin/puppetforge/package.py
vdt/versionplugin/puppetforge/shared.py
vdt/versionplugin/puppetforge/version.py