Metadata-Version: 1.0
Name: vdt.versionplugin.puppetforge
Version: 0.2
Summary: Version Increment Plugin that builds a package from a puppet module from puppet forge
Home-page: UNKNOWN
Author: Lars van de Kerkhof
Author-email: lars@permanentmarkers.nl
License: UNKNOWN
Platform: UNKNOWN
